.gitignore
LICENSE
Makefile
README.md
pyproject.toml
setup.py
test.py
./subsets/BitSet.cpp
./subsets/DenseBox.cpp
./subsets/DenseSet.cpp
./subsets/DenseTernary.cpp
./subsets/subsets.i
subsets/BitSet.cpp
subsets/BitSet.hpp
subsets/DenseBox.cpp
subsets/DenseBox.hpp
subsets/DenseSet.cpp
subsets/DenseSet.hpp
subsets/DenseTernary.cpp
subsets/DenseTernary.hpp
subsets/Sweep.hpp
subsets/Sweep3.hpp
subsets/__init__.py
subsets/common.hpp
subsets/hackycpp.hpp
subsets/max_cubes.py
subsets/subsets.i
subsets/subsets.py
subsets/ternary.hpp
subsets/tools.py
subsets.egg-info/PKG-INFO
subsets.egg-info/SOURCES.txt
subsets.egg-info/dependency_links.txt
subsets.egg-info/entry_points.txt
subsets.egg-info/requires.txt
subsets.egg-info/top_level.txt
tests/test_DenseBox.py
tests/test_DenseSet.py
tests/test_MaxCubes.py