Metadata-Version: 2.1
Name: subsets
Version: 1.1.2
Summary: Tools for cryptanalysis (subsets & transforms)
Author-email: Aleksei Udovenko <aleksei@affine.group>
License: MIT License
Project-URL: Repository, https://github.com/hellman/subsets
Keywords: subsets,binary,ternary,multidimensional transforms,cryptanalysis,cryptography
Requires-Python: >=3.7
License-File: LICENSE
Requires-Dist: binteger>=0.8.0
